Metadata-Version: 2.1
Name: oneNeuron-pypi-harshyadav1508
Version: 0.0.3
Summary: Implementation of perceptron
Home-page: https://github.com/harshyadav1508/oneNeuron_pypi
Author: harshyadav1508
Author-email: yaduvanshiharsh15@gmail.com
License: UNKNOWN
Project-URL: Bug Tracker, https://github.com/harshyadav1508/oneNeuron_pypi/issues
Platform: UNKNOWN
Classifier: Programming Language :: Python :: 3
Classifier: License :: OSI Approved :: MIT License
Classifier: Operating System :: OS Independent
Requires-Python: >=3.7
License-File: LICENSE
Requires-Dist: numpy
Requires-Dist: tqdm
